twinn_ml_interface/__init__.py
twinn_ml_interface/_version.py
twinn_ml_interface/input_data/__init__.py
twinn_ml_interface/input_data/input_data.py
twinn_ml_interface/input_data/utils.py
twinn_ml_interface/interface/__init__.py
twinn_ml_interface/interface/model_interfaces.py
twinn_ml_interface/interface/model_test.py
twinn_ml_interface/interface_validation/__init__.py
twinn_ml_interface/interface_validation/mock_predict_executor.py
twinn_ml_interface/interface_validation/mock_train_executor.py
twinn_ml_interface/interface_validation/test_model_interface.py
twinn_ml_interface/mocks/__init__.py
twinn_ml_interface/mocks/mocks.py
twinn_ml_interface/objectmodels/__init__.py
twinn_ml_interface/objectmodels/configuration.py
twinn_ml_interface/objectmodels/exceptions.py
twinn_ml_interface/objectmodels/hierarchy.py
twinn_ml_interface/objectmodels/logging.py
twinn_ml_interface/objectmodels/model_flags.py
twinn_ml_interface-0.7.0.dist-info/licenses/LICENSE
twinn_ml_interface-0.7.0.dist-info/METADATA
twinn_ml_interface-0.7.0.dist-info/WHEEL
twinn_ml_interface-0.7.0.dist-info/top_level.txt
twinn_ml_interface-0.7.0.dist-info/RECORD
