Metadata-Version: 2.4
Name: twinn-ml-interface
Version: 0.7.0
Summary: Machine learning model contracts with machine learning infrastructure
License: MIT
Project-URL: homepage, https://github.com/RoyalHaskoningDHV/twinn-ml-interface
Project-URL: issues, https://github.com/RoyalHaskoningDHV/twinn-ml-interface/issues
Project-URL: discussions, https://github.com/RoyalHaskoningDHV/twinn-ml-interface/discussions
Classifier: Programming Language :: Python :: 3
Classifier: Programming Language :: Python :: 3 :: Only
Classifier: Programming Language :: Python :: 3.10
Classifier: Programming Language :: Python :: 3.11
Classifier: Programming Language :: Python :: 3.12
Classifier: License :: OSI Approved :: MIT License
Classifier: Operating System :: OS Independent
Requires-Python: <3.13,>=3.10
License-File: LICENSE
Requires-Dist: annotation-protocol
Requires-Dist: matplotlib
Requires-Dist: pandas
Dynamic: license-file
